pdf_image_retrieval/__init__.py
pdf_image_retrieval/extractor.py
pdf_image_retrieval/keyword_extractor.py
pdf_image_retrieval/retriever.py
pdf_image_retrieval/s3_manager.py
tests/__init__.py
tests/test_extractor.py
tests/test_retriever.py
pdf_image_retrieval-0.1.0.dist-info/METADATA
pdf_image_retrieval-0.1.0.dist-info/WHEEL
pdf_image_retrieval-0.1.0.dist-info/top_level.txt
pdf_image_retrieval-0.1.0.dist-info/RECORD
