Metadata-Version: 2.4
Name: pdf-image-retrieval
Version: 0.1.0
Summary: Extracts images from PDFs, stores them in S3, and retrieves based on keyword search
Home-page: https://github.com/aryandhandhukiya/pdf-image-retrieval
Author: Aryan Dhandhukiya
Author-email: dhandhukiyaaryan05@gmail.com
Classifier: Programming Language :: Python :: 3
Classifier: License :: OSI Approved :: MIT License
Classifier: Operating System :: OS Independent
Requires-Python: >=3.6
Requires-Dist: fitz
Requires-Dist: pdf2image
Requires-Dist: Pillow
Requires-Dist: boto3
Requires-Dist: nltk
Dynamic: author
Dynamic: author-email
Dynamic: classifier
Dynamic: description
Dynamic: description-content-type
Dynamic: home-page
Dynamic: requires-dist
Dynamic: requires-python
Dynamic: summary
